bibolamazi/__init__.py
bibolamazi/init.py
bibolamazi/core/__init__.py
bibolamazi/core/argparseactions.py
bibolamazi/core/bibolamazifile.py
bibolamazi/core/blogger.py
bibolamazi/core/butils.py
bibolamazi/core/main.py
bibolamazi/core/version.py
bibolamazi/core/bibfilter/__init__.py
bibolamazi/core/bibfilter/argtypes.py
bibolamazi/core/bibfilter/factory.py
bibolamazi/core/bibusercache/__init__.py
bibolamazi/core/bibusercache/tokencheckers.py
bibolamazi/filters/__init__.py
bibolamazi/filters/arxiv.py
bibolamazi/filters/citearxiv.py
bibolamazi/filters/citeinspirehep.py
bibolamazi/filters/citekey.py
bibolamazi/filters/duplicates.py
bibolamazi/filters/echo.py
bibolamazi/filters/fixes.py
bibolamazi/filters/nameinitials.py
bibolamazi/filters/only_used.py
bibolamazi/filters/orderentries.py
bibolamazi/filters/url.py
bibolamazi/filters/util/__init__.py
bibolamazi/filters/util/arxivutil.py
bibolamazi/filters/util/auxfile.py
bibolamazi/filters/util/entryfmt.py
bibolamazi-3.2.post1.data/scripts/bibolamazi
bibolamazi-3.2.post1.dist-info/DESCRIPTION.rst
bibolamazi-3.2.post1.dist-info/METADATA
bibolamazi-3.2.post1.dist-info/metadata.json
bibolamazi-3.2.post1.dist-info/RECORD
bibolamazi-3.2.post1.dist-info/top_level.txt
bibolamazi-3.2.post1.dist-info/WHEEL
bibolamazi-3.2.post1.dist-info/zip-safe
