Metadata-Version: 2.0
Name: bibolamazi
Version: 3.2.post1
Summary: Prepare consistent BibTeX files for your LaTeX documents
Home-page: https://github.com/phfaist/bibolamazi/
Author: Philippe Faist
Author-email: philippe.faist@bluewin.ch
License: GPL v3+
Keywords: bibtex latex bibliography consistent tidy formatting
Platform: UNKNOWN
Classifier: Development Status :: 5 - Production/Stable
Classifier: License :: OSI Approved :: GNU General Public License v3 or later (GPLv3+)
Classifier: Programming Language :: Python
Classifier: Operating System :: OS Independent
Classifier: Intended Audience :: Science/Research
Classifier: Topic :: Scientific/Engineering
Classifier: Topic :: Text Editors :: Text Processing
Classifier: Topic :: Text Processing :: General
Requires-Dist: pybtex (>=0.16)
Requires-Dist: arxiv2bib (>=1.0.2)
Requires-Dist: pylatexenc (>=0.9)
